gpforecast/__init__.py
gpforecast/gp.py
gpforecast-1.0.2.dist-info/METADATA
gpforecast-1.0.2.dist-info/WHEEL
gpforecast-1.0.2.dist-info/top_level.txt
gpforecast-1.0.2.dist-info/RECORD
