Metadata-Version: 2.1
Name: gpforecast
Version: 1.0.2
Summary: Time series forecasting with Gaussian Processes
Home-page: https://github.com/IDSIA/gpforecasting
Author: Huber David, Rubattu Nicolo', Corani Giorgio
Author-email: david.huber@idsia.ch, nicolo.rubattu@idsia.ch, giorgio.corani@idsia.ch
License: BSD License
Platform: UNKNOWN
Classifier: License :: OSI Approved :: BSD License
Classifier: Programming Language :: Python :: 3.8
Requires-Dist: numpy
Requires-Dist: pandas
Requires-Dist: scipy
Requires-Dist: GPy
Requires-Dist: properscoring
Requires-Dist: matplotlib
Requires-Dist: packaging
